{
  "commit": "f30bb7dfa0e355324f62c0adbaadbcf0a4f45a35",
  "generated": "2023-11-29T01:01:34.352Z",
  "metadata": [
    {
      "__outstatic": {
        "commit": "5002025d683605614a2d4f048d712bd4b6ec0d96",
        "hash": "4293994784",
        "path": "outstatic/content/posts/membongkar-keunggulan-nextjs-masa-depan-pengembangan-web-yang-efisien.md"
      },
      "author": {
        "name": "Ghazi Taqiyya Al Anshari",
        "picture": "https://avatars.githubusercontent.com/u/64888591?v=4"
      },
      "collection": "posts",
      "coverImage": "/images/nextjs-banner-c1OT.png",
      "description": "",
      "publishedAt": "2023-11-28T14:29:57.297Z",
      "slug": "membongkar-keunggulan-nextjs-masa-depan-pengembangan-web-yang-efisien",
      "status": "published",
      "title": "Membongkar Keunggulan Next.js: Masa Depan Pengembangan Web yang Efisien"
    },
    {
      "__outstatic": {
        "commit": "2d0d19b3305cbd3b2c308e7ed2f183d4a35a81a4",
        "hash": "1878423185",
        "path": "outstatic/content/posts/membangun-aplikasi-web-scalable-dengan-nestjs-framework-nodejs-yang-kuat.md"
      },
      "author": {
        "name": "Ghazi Taqiyya Al Anshari",
        "picture": "https://avatars.githubusercontent.com/u/64888591?v=4"
      },
      "collection": "posts",
      "coverImage": "/images/nestjs-AxOD.jpeg",
      "description": "",
      "publishedAt": "2023-11-28T14:33:30.253Z",
      "slug": "membangun-aplikasi-web-scalable-dengan-nestjs-framework-nodejs-yang-kuat",
      "status": "published",
      "title": "Membangun Aplikasi Web Scalable dengan NestJS: Framework Node.js yang Kuat"
    },
    {
      "__outstatic": {
        "commit": "f30bb7dfa0e355324f62c0adbaadbcf0a4f45a35",
        "hash": "2894430490",
        "path": "outstatic/content/posts/membangun-aplikasi-web-modern-dengan-nuxtjs-menggali-potensi-framework-vuejs-yang-kuat.md"
      },
      "author": {
        "name": "Ghazi Taqiyya Al Anshari",
        "picture": "https://avatars.githubusercontent.com/u/64888591?v=4"
      },
      "collection": "posts",
      "coverImage": "/images/nuxtjs-YwNT.webp",
      "description": "",
      "publishedAt": "2023-11-29T01:42:01.460Z",
      "slug": "membangun-aplikasi-web-modern-dengan-nuxtjs-menggali-potensi-framework-vuejs-yang-kuat",
      "status": "draft",
      "title": "Membangun Aplikasi Web Modern dengan Nuxt.js: Menggali Potensi Framework Vue.js yang Kuat"
    }
  ]
}